sml_small/__init__.py
sml_small/date_adjustment.py
sml_small/editing/__init__.py
sml_small/editing/thousand_pounds/README.md
sml_small/editing/thousand_pounds/__init__.py
sml_small/editing/thousand_pounds/thousand_pounds.py
sml_small/editing/totals_and_components/README.md
sml_small/editing/totals_and_components/__init__.py
sml_small/editing/totals_and_components/totals_and_components.py
sml_small/logging.conf
sml_small/selective_editing.py
sml_small/utils/__init__.py
sml_small/utils/common_utils.py
sml_small/utils/error_utils.py
sml_small/utils/pandas_example.py
sml_small/utils/pandas_wrapper.py
sml_small-1.2.5.dist-info/LICENSE
sml_small-1.2.5.dist-info/WHEEL
sml_small-1.2.5.dist-info/METADATA
sml_small-1.2.5.dist-info/RECORD
