Metadata-Version: 2.1
Name: sml-small
Version: 1.2.5
Summary: SML Small (Python Pandas methods)
Requires-Python: >=3.9,<=3.13
Classifier: Programming Language :: Python :: 3
Classifier: Programming Language :: Python :: 3.9
Classifier: Programming Language :: Python :: 3.10
Classifier: Programming Language :: Python :: 3.11
Requires-Dist: numpy (>=1.26.1,<2.0.0)
Requires-Dist: pandas (>=1.3.5,<2.0.0)
Requires-Dist: regex (>=2024.4.16,<2025.0.0)
